CHANGES.rst
MANIFEST.in
README.rst
setup.py
src/collective/__init__.py
src/collective.usernamelogger.egg-info/PKG-INFO
src/collective.usernamelogger.egg-info/SOURCES.txt
src/collective.usernamelogger.egg-info/dependency_links.txt
src/collective.usernamelogger.egg-info/entry_points.txt
src/collective.usernamelogger.egg-info/namespace_packages.txt
src/collective.usernamelogger.egg-info/not-zip-safe
src/collective.usernamelogger.egg-info/requires.txt
src/collective.usernamelogger.egg-info/top_level.txt
src/collective/usernamelogger/__init__.py
src/collective/usernamelogger/browser.txt
src/collective/usernamelogger/configure.zcml
src/collective/usernamelogger/tests.py