Metadata-Version: 1.1
Name: collective.usernamelogger
Version: 1.4
Summary: Log user names when using cookie authentication in Zope/Plone.
Home-page: http://pypi.python.org/pypi/collective.usernamelogger
Author: Andreas Zeidler
Author-email: az@zitc.de
License: BSD
Keywords: zope plone logging pas
Platform: Any
Classifier: Development Status :: 5 - Production/Stable
Classifier: Environment :: Web Environment
Classifier: Framework :: Plone
Classifier: Framework :: Zope2
Classifier: Intended Audience :: System Administrators
Classifier: Intended Audience :: Other Audience
Classifier: License :: OSI Approved :: Zope Public License
Classifier: Operating System :: OS Independent
Classifier: Programming Language :: Python
Classifier: Topic :: Software Development :: Libraries :: Python Modules
